{
  "bg": 160, 
  "temp": "absolute", 
  "snoozeBG": 182, 
  "timestamp": "2016-07-29T08:59:50.914253", 
  "missing": [
    "duration", 
    "rate"
  ], 
  "predBGs": {
    "IOB": [
      160, 
      165, 
      170, 
      173, 
      177, 
      179, 
      181, 
      183, 
      184, 
      184, 
      184, 
      182, 
      181, 
      179, 
      177, 
      175, 
      173, 
      171, 
      169, 
      167, 
      165, 
      163, 
      161, 
      160, 
      158, 
      156, 
      154, 
      152, 
      151, 
      149, 
      148, 
      146, 
      145, 
      143, 
      142, 
      140, 
      139, 
      138, 
      137, 
      136, 
      135, 
      134, 
      133, 
      132, 
      131, 
      131, 
      131, 
      131, 
      130
    ]
  }, 
  "reason": "COB: 0, Dev: 37, BGI: -0.5, ISF: 1.8, Target: 6.5; Eventual BG 8.7 >= 7, adj. req. rate: 3.45 to maxSafeBasal: 1.8, temp 1.8 >~ req 1.8U/hr", 
  "COB": 0, 
  "eventualBG": 157, 
  "error": "missing required input fields", 
  "input": {
    "bg": 160, 
    "temp": "absolute", 
    "snoozeBG": 182, 
    "predBGs": {
      "IOB": [
        160, 
        165, 
        170, 
        173, 
        177, 
        179, 
        181, 
        183, 
        184, 
        184, 
        184, 
        182, 
        181, 
        179, 
        177, 
        175, 
        173, 
        171, 
        169, 
        167, 
        165, 
        163, 
        161, 
        160, 
        158, 
        156, 
        154, 
        152, 
        151, 
        149, 
        148, 
        146, 
        145, 
        143, 
        142, 
        140, 
        139, 
        138, 
        137, 
        136, 
        135, 
        134, 
        133, 
        132, 
        131, 
        131, 
        131, 
        131, 
        130
      ]
    }, 
    "reason": "COB: 0, Dev: 37, BGI: -0.5, ISF: 1.8, Target: 6.5; Eventual BG 8.7 >= 7, adj. req. rate: 3.45 to maxSafeBasal: 1.8, temp 1.8 >~ req 1.8U/hr", 
    "COB": 0, 
    "eventualBG": 157, 
    "tick": "+4", 
    "IOB": 1.244
  }, 
  "tick": "+4", 
  "IOB": 1.244
}