[
  {
    "netbasalinsulin": 0.3, 
    "activity": 0.0012, 
    "basaliob": 0.006, 
    "time": "2016-07-30T18:52:11.000Z", 
    "hightempinsulin": 0.35, 
    "bolussnooze": 0, 
    "iob": 0.006
  }, 
  {
    "netbasalinsulin": 0.3, 
    "activity": 0.0011, 
    "basaliob": 0.004, 
    "time": "2016-07-30T18:57:11.000Z", 
    "hightempinsulin": 0.35, 
    "bolussnooze": 0, 
    "iob": 0.004
  }, 
  {
    "netbasalinsulin": 0.3, 
    "activity": 0.0011, 
    "basaliob": 0.003, 
    "time": "2016-07-30T19:02:11.000Z", 
    "hightempinsulin": 0.35, 
    "bolussnooze": 0, 
    "iob": 0.003
  }, 
  {
    "netbasalinsulin": 0.2, 
    "activity": 0.0007, 
    "basaliob": 0.002, 
    "time": "2016-07-30T19:07:11.000Z", 
    "hightempinsulin": 0.25, 
    "bolussnooze": 0, 
    "iob": 0.002
  }, 
  {
    "netbasalinsulin": 0.1, 
    "activity": 0.0004, 
    "basaliob": 0.001, 
    "time": "2016-07-30T19:12:11.000Z", 
    "hightempinsulin": 0.15, 
    "bolussnooze": 0, 
    "iob": 0.001
  }, 
  {
    "netbasalinsulin": 0.1, 
    "activity": 0.0004, 
    "basaliob": 0.001, 
    "time": "2016-07-30T19:17:11.000Z", 
    "hightempinsulin": 0.15, 
    "bolussnooze": 0, 
    "iob": 0.001
  }, 
  {
    "netbasalinsulin": 0.1, 
    "activity": 0.0004, 
    "basaliob": 0, 
    "time": "2016-07-30T19:22:11.000Z", 
    "hightempinsulin": 0.15, 
    "bolussnooze": 0, 
    "iob": 0
  }, 
  {
    "netbasalinsulin": 0.1, 
    "activity": 0.0003, 
    "basaliob": 0, 
    "time": "2016-07-30T19:27:11.000Z", 
    "hightempinsulin": 0.15, 
    "bolussnooze": 0, 
    "iob": 0
  }, 
  {
    "netbasalinsulin": 0.05, 
    "activity": 0.0002, 
    "basaliob": 0, 
    "time": "2016-07-30T19:32:11.000Z", 
    "hightempinsulin": 0.1, 
    "bolussnooze": 0, 
    "iob": 0
  }, 
  {
    "netbasalinsulin": 0.05, 
    "activity": 0.0002, 
    "basaliob": 0, 
    "time": "2016-07-30T19:37:11.000Z", 
    "hightempinsulin": 0.1, 
    "bolussnooze": 0, 
    "iob": 0
  }, 
  {
    "netbasalinsulin": 0.05, 
    "activity": 0.0002, 
    "basaliob": 0, 
    "time": "2016-07-30T19:42:11.000Z", 
    "hightempinsulin": 0.1, 
    "bolussnooze": 0, 
    "iob": 0
  }, 
  {
    "netbasalinsulin": 0, 
    "activity": 0, 
    "basaliob": 0, 
    "time": "2016-07-30T19:47:11.000Z", 
    "hightempinsulin": 0.05, 
    "bolussnooze": 0, 
    "iob": 0
  }, 
  {
    "netbasalinsulin": -0.05, 
    "activity": -0.0002, 
    "basaliob": 0, 
    "time": "2016-07-30T19:52:11.000Z", 
    "hightempinsulin": 0, 
    "bolussnooze": 0, 
    "iob": 0
  }, 
  {
    "netbasalinsulin": 0, 
    "activity": 0, 
    "basaliob": 0, 
    "time": "2016-07-30T19:57:11.000Z", 
    "hightempinsulin": 0, 
    "bolussnooze": 0, 
    "iob": 0
  }, 
  {
    "netbasalinsulin": 0, 
    "activity": 0, 
    "basaliob": 0, 
    "time": "2016-07-30T20:02:11.000Z", 
    "hightempinsulin": 0, 
    "bolussnooze": 0, 
    "iob": 0
  }, 
  {
    "netbasalinsulin": 0, 
    "activity": 0, 
    "basaliob": 0, 
    "time": "2016-07-30T20:07:11.000Z", 
    "hightempinsulin": 0, 
    "bolussnooze": 0, 
    "iob": 0
  }, 
  {
    "netbasalinsulin": 0, 
    "activity": 0, 
    "basaliob": 0, 
    "time": "2016-07-30T20:12:11.000Z", 
    "hightempinsulin": 0, 
    "bolussnooze": 0, 
    "iob": 0
  }, 
  {
    "netbasalinsulin": 0, 
    "activity": 0, 
    "basaliob": 0, 
    "time": "2016-07-30T20:17:11.000Z", 
    "hightempinsulin": 0, 
    "bolussnooze": 0, 
    "iob": 0
  }, 
  {
    "netbasalinsulin": 0, 
    "activity": 0, 
    "basaliob": 0, 
    "time": "2016-07-30T20:22:11.000Z", 
    "hightempinsulin": 0, 
    "bolussnooze": 0, 
    "iob": 0
  }, 
  {
    "netbasalinsulin": 0, 
    "activity": 0, 
    "basaliob": 0, 
    "time": "2016-07-30T20:27:11.000Z", 
    "hightempinsulin": 0, 
    "bolussnooze": 0, 
    "iob": 0
  }, 
  {
    "netbasalinsulin": 0, 
    "activity": 0, 
    "basaliob": 0, 
    "time": "2016-07-30T20:32:11.000Z", 
    "hightempinsulin": 0, 
    "bolussnooze": 0, 
    "iob": 0
  }, 
  {
    "netbasalinsulin": 0, 
    "activity": 0, 
    "basaliob": 0, 
    "time": "2016-07-30T20:37:11.000Z", 
    "hightempinsulin": 0, 
    "bolussnooze": 0, 
    "iob": 0
  }, 
  {
    "netbasalinsulin": 0, 
    "activity": 0, 
    "basaliob": 0, 
    "time": "2016-07-30T20:42:11.000Z", 
    "hightempinsulin": 0, 
    "bolussnooze": 0, 
    "iob": 0
  }, 
  {
    "netbasalinsulin": 0, 
    "activity": 0, 
    "basaliob": 0, 
    "time": "2016-07-30T20:47:11.000Z", 
    "hightempinsulin": 0, 
    "bolussnooze": 0, 
    "iob": 0
  }, 
  {
    "netbasalinsulin": 0, 
    "activity": 0, 
    "basaliob": 0, 
    "time": "2016-07-30T20:52:11.000Z", 
    "hightempinsulin": 0, 
    "bolussnooze": 0, 
    "iob": 0
  }, 
  {
    "netbasalinsulin": 0, 
    "activity": 0, 
    "basaliob": 0, 
    "time": "2016-07-30T20:57:11.000Z", 
    "hightempinsulin": 0, 
    "bolussnooze": 0, 
    "iob": 0
  }, 
  {
    "netbasalinsulin": 0, 
    "activity": 0, 
    "basaliob": 0, 
    "time": "2016-07-30T21:02:11.000Z", 
    "hightempinsulin": 0, 
    "bolussnooze": 0, 
    "iob": 0
  }, 
  {
    "netbasalinsulin": 0, 
    "activity": 0, 
    "basaliob": 0, 
    "time": "2016-07-30T21:07:11.000Z", 
    "hightempinsulin": 0, 
    "bolussnooze": 0, 
    "iob": 0
  }, 
  {
    "netbasalinsulin": 0, 
    "activity": 0, 
    "basaliob": 0, 
    "time": "2016-07-30T21:12:11.000Z", 
    "hightempinsulin": 0, 
    "bolussnooze": 0, 
    "iob": 0
  }, 
  {
    "netbasalinsulin": 0, 
    "activity": 0, 
    "basaliob": 0, 
    "time": "2016-07-30T21:17:11.000Z", 
    "hightempinsulin": 0, 
    "bolussnooze": 0, 
    "iob": 0
  }, 
  {
    "netbasalinsulin": 0, 
    "activity": 0, 
    "basaliob": 0, 
    "time": "2016-07-30T21:22:11.000Z", 
    "hightempinsulin": 0, 
    "bolussnooze": 0, 
    "iob": 0
  }, 
  {
    "netbasalinsulin": 0, 
    "activity": 0, 
    "basaliob": 0, 
    "time": "2016-07-30T21:27:11.000Z", 
    "hightempinsulin": 0, 
    "bolussnooze": 0, 
    "iob": 0
  }, 
  {
    "netbasalinsulin": 0, 
    "activity": 0, 
    "basaliob": 0, 
    "time": "2016-07-30T21:32:11.000Z", 
    "hightempinsulin": 0, 
    "bolussnooze": 0, 
    "iob": 0
  }, 
  {
    "netbasalinsulin": 0, 
    "activity": 0, 
    "basaliob": 0, 
    "time": "2016-07-30T21:37:11.000Z", 
    "hightempinsulin": 0, 
    "bolussnooze": 0, 
    "iob": 0
  }, 
  {
    "netbasalinsulin": 0, 
    "activity": 0, 
    "basaliob": 0, 
    "time": "2016-07-30T21:42:11.000Z", 
    "hightempinsulin": 0, 
    "bolussnooze": 0, 
    "iob": 0
  }, 
  {
    "netbasalinsulin": 0, 
    "activity": 0, 
    "basaliob": 0, 
    "time": "2016-07-30T21:47:11.000Z", 
    "hightempinsulin": 0, 
    "bolussnooze": 0, 
    "iob": 0
  }, 
  {
    "netbasalinsulin": 0, 
    "activity": 0, 
    "basaliob": 0, 
    "time": "2016-07-30T21:52:11.000Z", 
    "hightempinsulin": 0, 
    "bolussnooze": 0, 
    "iob": 0
  }, 
  {
    "netbasalinsulin": 0, 
    "activity": 0, 
    "basaliob": 0, 
    "time": "2016-07-30T21:57:11.000Z", 
    "hightempinsulin": 0, 
    "bolussnooze": 0, 
    "iob": 0
  }, 
  {
    "netbasalinsulin": 0, 
    "activity": 0, 
    "basaliob": 0, 
    "time": "2016-07-30T22:02:11.000Z", 
    "hightempinsulin": 0, 
    "bolussnooze": 0, 
    "iob": 0
  }, 
  {
    "netbasalinsulin": 0, 
    "activity": 0, 
    "basaliob": 0, 
    "time": "2016-07-30T22:07:11.000Z", 
    "hightempinsulin": 0, 
    "bolussnooze": 0, 
    "iob": 0
  }, 
  {
    "netbasalinsulin": 0, 
    "activity": 0, 
    "basaliob": 0, 
    "time": "2016-07-30T22:12:11.000Z", 
    "hightempinsulin": 0, 
    "bolussnooze": 0, 
    "iob": 0
  }, 
  {
    "netbasalinsulin": 0, 
    "activity": 0, 
    "basaliob": 0, 
    "time": "2016-07-30T22:17:11.000Z", 
    "hightempinsulin": 0, 
    "bolussnooze": 0, 
    "iob": 0
  }, 
  {
    "netbasalinsulin": 0, 
    "activity": 0, 
    "basaliob": 0, 
    "time": "2016-07-30T22:22:11.000Z", 
    "hightempinsulin": 0, 
    "bolussnooze": 0, 
    "iob": 0
  }, 
  {
    "netbasalinsulin": 0, 
    "activity": 0, 
    "basaliob": 0, 
    "time": "2016-07-30T22:27:11.000Z", 
    "hightempinsulin": 0, 
    "bolussnooze": 0, 
    "iob": 0
  }, 
  {
    "netbasalinsulin": 0, 
    "activity": 0, 
    "basaliob": 0, 
    "time": "2016-07-30T22:32:11.000Z", 
    "hightempinsulin": 0, 
    "bolussnooze": 0, 
    "iob": 0
  }, 
  {
    "netbasalinsulin": 0, 
    "activity": 0, 
    "basaliob": 0, 
    "time": "2016-07-30T22:37:11.000Z", 
    "hightempinsulin": 0, 
    "bolussnooze": 0, 
    "iob": 0
  }, 
  {
    "netbasalinsulin": 0, 
    "activity": 0, 
    "basaliob": 0, 
    "time": "2016-07-30T22:42:11.000Z", 
    "hightempinsulin": 0, 
    "bolussnooze": 0, 
    "iob": 0
  }, 
  {
    "netbasalinsulin": 0, 
    "activity": 0, 
    "basaliob": 0, 
    "time": "2016-07-30T22:47:11.000Z", 
    "hightempinsulin": 0, 
    "bolussnooze": 0, 
    "iob": 0
  }
]